gigagan_pytorch/__init__.py
gigagan_pytorch/attend.py
gigagan_pytorch/data.py
gigagan_pytorch/distributed.py
gigagan_pytorch/gigagan_pytorch.py
gigagan_pytorch/open_clip.py
gigagan_pytorch/optimizer.py
gigagan_pytorch/unet_upsampler.py
gigagan_pytorch/version.py
gigagan_pytorch-0.3.0.dist-info/LICENSE
gigagan_pytorch-0.3.0.dist-info/METADATA
gigagan_pytorch-0.3.0.dist-info/WHEEL
gigagan_pytorch-0.3.0.dist-info/top_level.txt
gigagan_pytorch-0.3.0.dist-info/RECORD
