Metadata-Version: 2.2
Name: gigagan-pytorch
Version: 0.3.0
Summary: GigaGAN - Pytorch
Home-page: https://github.com/lucidrains/ETSformer-pytorch
Author: Phil Wang
Author-email: lucidrains@gmail.com
License: MIT
Keywords: artificial intelligence,deep learning,generative adversarial networks
Classifier: Development Status :: 4 - Beta
Classifier: Intended Audience :: Developers
Classifier: Topic :: Scientific/Engineering :: Artificial Intelligence
Classifier: License :: OSI Approved :: MIT License
Classifier: Programming Language :: Python :: 3.6
License-File: LICENSE
Requires-Dist: accelerate
Requires-Dist: beartype
Requires-Dist: einops>=0.6
Requires-Dist: ema-pytorch
Requires-Dist: kornia
Requires-Dist: numerize
Requires-Dist: open-clip-torch<3.0.0,>=2.0.0
Requires-Dist: pillow
Requires-Dist: torch>=1.6
Requires-Dist: torchvision
Requires-Dist: tqdm
Dynamic: author
Dynamic: author-email
Dynamic: classifier
Dynamic: description-content-type
Dynamic: home-page
Dynamic: keywords
Dynamic: license
Dynamic: requires-dist
Dynamic: summary
